bedsy/__init__.py
bedsy/bedsy.py
bedsy-0.2b1.dist-info/METADATA
bedsy-0.2b1.dist-info/WHEEL
bedsy-0.2b1.dist-info/licenses/LICENSE
bedsy-0.2b1.dist-info/RECORD
