Metadata-Version: 2.1
Name: bedsy
Version: 0.2b1
Summary: The BeDSy is a platform for hardware triggering and synchronisation of equipment for laboratory animal behavioural monitoring.
Project-URL: Homepage, https://github.com/davorvr/bedsy
Project-URL: Bug Tracker, https://github.com/davorvr/bedsy/issues
Author-email: Davor Virag <davor.virag@gmail.com>
License-File: LICENSE
Classifier: Intended Audience :: Science/Research
Classifier: License :: OSI Approved :: GNU General Public License v3 (GPLv3)
Classifier: Operating System :: OS Independent
Classifier: Programming Language :: Python :: 3
Classifier: Topic :: Scientific/Engineering
Requires-Python: >=3.11
Requires-Dist: pyserial>=3.5
